{"name":"Guido","surname":"Rimez","birthday":"2004-09-16","pesel":"12345","medicine":[{"name":"Lek","dose":"4","from":1585612800,"to":1586908800}],"checkups":[],"_id":"WfWuPDi3ss8QUdVq"}
{"name":"Mario","surname":"Brada","birthday":"1970-01-28","pesel":"54321","medicine":[{"name":"Ibuprofen","dose":"3","from":1583798400,"to":1584662400},{"name":"Ibuprofen","dose":"3","from":1583798400,"to":1584662400},{"name":"Paracetamol","dose":"2","from":1580947200,"to":1581552000},{"name":"Aug","dose":"3","from":1583798400,"to":1584662400},{"name":"aug","dose":"1","from":1584662400,"to":1583971200},{"name":"au","dose":"1","from":1585612800,"to":1583971200},{"name":"aug","dose":"1","from":1585094400,"to":1584576000}],"checkups":[{"description":"Echo od kardiologa","date":1584576000,"details":"sciezka.pdf"}],"_id":"nTpTCvGPQ120HtS0"}
{"name":"Ricardo","surname":"Colucci","birthday":"1986-08-07","pesel":"55555","medicine":[],"checkups":[],"_id":"qIO7wCJxJEYyjRUc"}
{"name":"Lucio","surname":"Estos","birthday":"1985-05-01","pesel":"77777","medicine":[],"checkups":[],"_id":"uK7eP72kUx2zJT4a"}
